Metadata-Version: 1.2
Name: pypop
Version: 0.1.1
Summary: A python library to compose pop songs automatically.
Home-page: https://github.com/yuma-m/pypop
Author: Yuma Mihira
License: MIT
Keywords: music pops
Platform: UNKNOWN
Classifier: Development Status :: 2 - Pre-Alpha
Classifier: Environment :: Console
Classifier: Intended Audience :: Developers
Classifier: Natural Language :: English
Classifier: Operating System :: OS Independent
Classifier: Topic :: Multimedia :: Sound/Audio
Classifier: License :: OSI Approved :: MIT License
Requires-Python: >=3.6
